LICENSE
MANIFEST.in
README.rst
setup.py
carrier/__init__.py
carrier/__main__.py
carrier/core.py
carrier/exceptions.py
carrier/processor.py
carrier/pypi.py
carrier/utils.py
carrier.egg-info/PKG-INFO
carrier.egg-info/SOURCES.txt
carrier.egg-info/dependency_links.txt
carrier.egg-info/entry_points.txt
carrier.egg-info/not-zip-safe
carrier.egg-info/requires.txt
carrier.egg-info/top_level.txt
carrier/config/__init__.py
carrier/config/defaults.py
carrier/config/pypi.crt
carrier/tasks/__init__.py
carrier/tasks/bulk.py