Metadata-Version: 1.0
Name: carrier
Version: 0.1.13
Summary: Warehouse and PyPI Synchronization
Home-page: https://github.com/crateio/carrier/
Author: Donald Stufft
Author-email: donald.stufft@gmail.com
License: Copyright (c) Donald Stufft
